pan_os_upgrade/__init__.py
pan_os_upgrade/assets/logo.png
pan_os_upgrade/components/__init__.py
pan_os_upgrade/components/assurance.py
pan_os_upgrade/components/device.py
pan_os_upgrade/components/ha.py
pan_os_upgrade/components/upgrade.py
pan_os_upgrade/components/utilities.py
pan_os_upgrade/main.py
pan_os_upgrade/models/__init__.py
pan_os_upgrade/models/arp_table.py
pan_os_upgrade/models/assurance_report.py
pan_os_upgrade/models/content_version.py
pan_os_upgrade/models/devices.py
pan_os_upgrade/models/ip_sec_tunnel.py
pan_os_upgrade/models/license.py
pan_os_upgrade/models/mixins.py
pan_os_upgrade/models/routes.py
pan_os_upgrade/models/session_stats.py
pan_os_upgrade-1.3.11.dist-info/LICENSE
pan_os_upgrade-1.3.11.dist-info/METADATA
pan_os_upgrade-1.3.11.dist-info/WHEEL
pan_os_upgrade-1.3.11.dist-info/entry_points.txt
pan_os_upgrade-1.3.11.dist-info/RECORD
