Metadata-Version: 2.3
Name: pan-os-upgrade
Version: 1.3.11
Summary: Python script to automate the upgrade process of PAN-OS firewalls.
License: Apache 2.0
Keywords: paloaltonetworks,panos,firewall,upgrade,automation
Author: Calvin Remsburg
Author-email: cremsburg.dev@gmail.com
Requires-Python: >=3.11,<4.0
Classifier: Development Status :: 4 - Beta
Classifier: Framework :: Flake8
Classifier: Framework :: MkDocs
Classifier: Framework :: Pydantic :: 2
Classifier: Intended Audience :: System Administrators
Classifier: License :: OSI Approved :: Apache Software License
Classifier: License :: Other/Proprietary License
Classifier: Natural Language :: English
Classifier: Operating System :: OS Independent
Classifier: Programming Language :: Python :: 3
Classifier: Programming Language :: Python :: 3.11
Classifier: Programming Language :: Python :: 3.12
Classifier: Programming Language :: Python :: 3.13
Classifier: Topic :: Software Development :: Libraries :: Python Modules
Classifier: Topic :: System :: Networking :: Firewalls
Classifier: Topic :: System :: Systems Administration
Classifier: Topic :: Utilities
Requires-Dist: colorama (>=0.4.6,<0.5.0)
Requires-Dist: dnspython (>=2.5.0,<3.0.0)
Requires-Dist: dynaconf (>=3.2.4,<4.0.0)
Requires-Dist: pan-os-python (>=1.11.0,<2.0.0)
Requires-Dist: panos-upgrade-assurance (>=1.1.0,<2.0.0)
Requires-Dist: prompt-toolkit (>=3.0.43,<4.0.0)
Requires-Dist: pydantic (>=2.5.3,<3.0.0)
Requires-Dist: pyyaml (>=6.0.1,<7.0.0)
Requires-Dist: reportlab (>=4.0.9,<5.0.0)
Requires-Dist: setuptools (>=69.0.3,<70.0.0)
Requires-Dist: tabulate (>=0.9.0,<0.10.0)
Requires-Dist: typer[all] (>=0.9.0,<0.10.0)
Project-URL: Documentation, https://cdot65.github.io/pan-os-upgrade/
